pulsepoint/StatsForecast.py
pulsepoint/__init__.py
pulsepoint/_modidx.py
pulsepoint/core.py
pulsepoint/tests.py
pulsepoint/utils.py
pulsepoint-0.0.1.dist-info/LICENSE
pulsepoint-0.0.1.dist-info/METADATA
pulsepoint-0.0.1.dist-info/WHEEL
pulsepoint-0.0.1.dist-info/entry_points.txt
pulsepoint-0.0.1.dist-info/top_level.txt
pulsepoint-0.0.1.dist-info/RECORD
