Metadata-Version: 2.1
Name: pulsepoint
Version: 0.0.1
Summary: Anomaly Detection Framework
Home-page: https://github.com/cooper-richason/pulsepoint
Author: Cooper Richason
Author-email: 144618753+cooper-richason@users.noreply.github.com
License: Apache Software License 2.0
Keywords: nbdev jupyter notebook python
Classifier: Development Status :: 4 - Beta
Classifier: Intended Audience :: Developers
Classifier: Natural Language :: English
Classifier: Programming Language :: Python :: 3.7
Classifier: Programming Language :: Python :: 3.8
Classifier: Programming Language :: Python :: 3.9
Classifier: Programming Language :: Python :: 3.10
Classifier: License :: OSI Approved :: Apache Software License
Requires-Python: >=3.7
License-File: LICENSE
Requires-Dist: fastcore
Requires-Dist: pandas
Requires-Dist: numpy
Requires-Dist: datetime
Requires-Dist: typing
Requires-Dist: pytz
Requires-Dist: statsforecast
Provides-Extra: dev
